{
    "server": "server ip or addres",
    "token_file_path": "./tokens.json",
    "device_codes": "deviceIds.json",
    "endpoints": {
        "get_rides": {
            "url": "/routes.json?device_code=",
            "delay": 0
        },
        "update_status": {
            "url": "/ride_points/",
            "delay": 3
        },
        "sign_in": {
            "url": "/sign_in.json?",
            "delay": 0
        },
        "register": {
            "url": "/devices",
            "delay": 0
        }
    }
}